wazender/__init__.py
wazender/app.py
wazender-0.6.0.dist-info/LICENSE
wazender-0.6.0.dist-info/METADATA
wazender-0.6.0.dist-info/WHEEL
wazender-0.6.0.dist-info/top_level.txt
wazender-0.6.0.dist-info/RECORD
