Metadata-Version: 2.1
Name: wazender
Version: 0.6.0
Summary: This package helps to send multiple whatsapp messages with attachments by Zan X Technologies
Author-email: Zandora Space <professor@zandora.space>
License: MIT License        
Project-URL: Homepage, https://github.com/zandora-space/wazender
Project-URL: Bug Tracker, https://github.com/zandora-space/wazender/issues
Classifier: Programming Language :: Python :: 3
Classifier: License :: OSI Approved :: MIT License
Classifier: Operating System :: OS Independent
Requires-Python: >=3.7
License-File: LICENSE
